MANIFEST.in
README.rst
setup.py
src/ppr/__init__.py
src/ppr/ga.py
src/ppr/geometry.py
src/ppr/geometry_pure_python.py
src/ppr/graph_pure_python.py
src/ppr/halton.py
src/ppr/optim.py
src/ppr/path.py
src/ppr/robot.py
src/ppr/sampling.py
src/ppr/util.py
src/ppr.egg-info/PKG-INFO
src/ppr.egg-info/SOURCES.txt
src/ppr.egg-info/dependency_links.txt
src/ppr.egg-info/requires.txt
src/ppr.egg-info/top_level.txt
src/ppr/cpp/__init__.py
src/ppr/cpp/geometry.i
src/ppr/cpp/geometry.py
src/ppr/cpp/graph.i
src/ppr/cpp/graph.py
src/ppr/cpp/numpy.i
src/ppr/cpp/include/geometry.h
src/ppr/cpp/include/graph.h
src/ppr/cpp/src/geometry.cpp
src/ppr/cpp/src/graph.cpp