Metadata-Version: 1.2
Name: ppr
Version: 0.2.1
Summary: Planar Python Robotics
Home-page: https://u0100037.pages.mech.kuleuven.be/planar_python_robotics/
Author: Jeroen De Maeyer
Author-email: jeroen.demaeyer@kuleuven.be
License: UNKNOWN
Download-URL: https://gitlab.mech.kuleuven.be/u0100037/planar_python_robotics/raw/master/dist/ppr-0.2.0.tar.gz
Keywords: robotics,motion planning
Platform: UNKNOWN
Requires-Python: >=3
